Metadata-Version: 1.1
Name: libreriasuma
Version: 0.0.1
Summary: Una suma
Home-page: UNKNOWN
Author: Usuario Test
Author-email: cuenta.medium@gmail.com
License: MIT
Keywords: suma
Platform: UNKNOWN
Classifier: Development Status :: 5 - Production/Stable
Classifier: Intended Audience :: Education
Classifier: License :: OSI Approved :: MIT License
Classifier: Programming Language :: Python :: 3
